chatgpt_cost_estimator/__init__.py
chatgpt_cost_estimator/main.py
chatgpt_cost_estimator/vision_cost_estimator.py
tests/__init__.py
tests/test_vision_calculate_cost.py
chatgpt_cost_estimator-0.1.6.dist-info/LICENSE
chatgpt_cost_estimator-0.1.6.dist-info/METADATA
chatgpt_cost_estimator-0.1.6.dist-info/WHEEL
chatgpt_cost_estimator-0.1.6.dist-info/entry_points.txt
chatgpt_cost_estimator-0.1.6.dist-info/top_level.txt
chatgpt_cost_estimator-0.1.6.dist-info/RECORD
