Metadata-Version: 2.1
Name: chatgpt-cost-estimator
Version: 0.1.6
Summary: A cost estimation tool for your ChatGPT Plus conversation history.
Home-page: https://github.com/npollock14/ChatGPT-Cost-Estimator
Author: Nathan Pollock
Author-email: ndpollock@wpi.edu
License: MIT
Classifier: Programming Language :: Python :: 3
Classifier: License :: OSI Approved :: MIT License
Requires-Python: >=3.11
License-File: LICENSE
Requires-Dist: asttokens >=2.4.1
Requires-Dist: certifi >=2023.7.22
Requires-Dist: charset-normalizer >=3.2.0
Requires-Dist: colorama >=0.4.6
Requires-Dist: executing >=2.0.1
Requires-Dist: icecream >=2.1.3
Requires-Dist: idna >=3.4
Requires-Dist: iniconfig >=2.0.0
Requires-Dist: numpy >=1.21.0
Requires-Dist: packaging >=23.2
Requires-Dist: pandas >=2.0.3
Requires-Dist: pluggy >=1.3.0
Requires-Dist: Pygments >=2.16.1
Requires-Dist: pytest >=7.4.3
Requires-Dist: python-dateutil >=2.8.2
Requires-Dist: pytz >=2023.3
Requires-Dist: regex >=2023.8.8
Requires-Dist: requests >=2.31.0
Requires-Dist: six >=1.16.0
Requires-Dist: tiktoken >=0.4.0
Requires-Dist: tzdata >=2023.3
Requires-Dist: urllib3 >=2.0.4
